MANIFEST.in
README.rst
setup.py
scripts/njic
src/nji/__init__.py
src/nji/javap.py
src/nji/jni.py
src/nji/scons.py
src/nji.egg-info/PKG-INFO
src/nji.egg-info/SOURCES.txt
src/nji.egg-info/dependency_links.txt
src/nji.egg-info/not-zip-safe
src/nji.egg-info/requires.txt
src/nji.egg-info/top_level.txt
src/nji/templates/clean.c
src/nji/templates/clean.h
src/nji/templates/default.c
src/nji/templates/default.h