Metadata-Version: 1.1
Name: nji
Version: 0.1.3
Summary: Native Java Interface code generator.
Home-page: https://github.com/greenbender/libnji
Author: greenbender
Author-email: byron.platt@gmail.com
License: BSD License
Platform: UNKNOWN
Classifier: Intended Audience :: Developers
Classifier: License :: OSI Approved :: BSD License
Classifier: Operating System :: OS Independent
Classifier: Programming Language :: Python
Classifier: Programming Language :: Python :: 2.7
